micro_toolkit/__init__.py
micro_toolkit/micro_toolkit.py
micro_toolkit/cache/__init__.py
micro_toolkit/cache/cache_me.py
micro_toolkit/concurrent/__init__.py
micro_toolkit/concurrent/rate_limited.py
micro_toolkit/concurrent/rate_limited_group.py
micro_toolkit/data_process/__init__.py
micro_toolkit/data_process/batch_iterator.py
micro_toolkit/data_process/merge_dict_list.py
micro_toolkit/data_process/text_sequence_padding.py
micro_toolkit/os/__init__.py
micro_toolkit/os/filesystem.py
micro_toolkit/runtime/__init__.py
micro_toolkit/runtime/import.py
micro_toolkit/sys/__init__.py
micro_toolkit/sys/argv.py
micro_toolkit-0.9.0.dist-info/AUTHORS.rst
micro_toolkit-0.9.0.dist-info/LICENSE
micro_toolkit-0.9.0.dist-info/METADATA
micro_toolkit-0.9.0.dist-info/WHEEL
micro_toolkit-0.9.0.dist-info/top_level.txt
micro_toolkit-0.9.0.dist-info/RECORD
